{"authorDailyContributionsMap":{"lrj689":[{"date":"2021-01-21","commitResults":[{"hash":"0330f55b8752b45cada9ac6e79796ae2b42e8015","messageTitle":"Update Duke","messageBody":"Added increment Level-1: Greet, Echo, Exit\n","fileTypesAndContributionMap":{"java":{"insertions":20,"deletions":1}}},{"hash":"bc23f77588a7239f829a7fb6be464c235d142d76","messageTitle":"Update Duke Level-1","messageBody":"tidy up code\n\nno functional changes\n","fileTypesAndContributionMap":{"java":{"insertions":9,"deletions":9}}},{"hash":"62544bc9357863148599b2a239f5d8a4a027d28a","messageTitle":"Added DukeList.java","messageBody":"Updated Duke.java\n\nDukeList class functions as a custom ArrayList to store user inputs\n\nDuke class updated to use DukeList class for user inputs and outputs\n","fileTypesAndContributionMap":{"java":{"insertions":29,"deletions":1}}},{"hash":"caa2194d87d684c87c6700d5130ee247d8f0049e","messageTitle":"Update DukeList.java with print method","messageBody":"Print method prints DukeList object in Duke.java\n","fileTypesAndContributionMap":{"java":{"insertions":4,"deletions":1}}},{"hash":"70db9dd18e6d5064a60de76836830aa5aadf86e5","messageTitle":"Added Task.java","messageBody":"Updated DukeList.java, Duke.java\n\nTask is a class representing a String and a boolean\n\nUpdated DukeList use Task objects\n","fileTypesAndContributionMap":{"java":{"insertions":55,"deletions":9}}},{"hash":"f6139d932923a8788a522dbfca7d2578a431f75e","messageTitle":"Add Deadlines.java, ToDos.java, Events.java","messageBody":"DukeList class: updated functionality to use new classes as mentioned above\n\nDuke class: cleaned up text output\n","fileTypesAndContributionMap":{"java":{"insertions":79,"deletions":18}}},{"hash":"27c5f7a3f757f5094d07b619b6fb85a9d79e1bc0","messageTitle":"Update runtest.bat","messageBody":"","fileTypesAndContributionMap":{"txt":{"insertions":5,"deletions":0},"java":{"insertions":1,"deletions":1},"bat":{"insertions":1,"deletions":0}}}]}]},"authorFileTypeContributionMap":{"lrj689":{"java":158,"md":0,"fxml":0,"sh":0,"bat":1,"gradle":0,"txt":5}},"authorContributionVariance":{"lrj689":4880.0825},"authorDisplayNameMap":{"lrj689":"LEE ..JIEH"}}
