{"authorDailyContributionsMap":{"kouyk":[{"date":"2021-01-17","commitResults":[{"hash":"75ea242d9a07b56f5f9dfba9bc46fc273412d3cd","messageTitle":"Duke.java: implement skeletal version","messageBody":"","tags":["Level-1"],"fileTypesAndContributionMap":{"java":{"insertions":34,"deletions":6}}},{"hash":"f02c9a890a9b023384371d505c63732e4d8989da","messageTitle":"Duke.java: store the commands given","messageBody":"","tags":["Level-2"],"fileTypesAndContributionMap":{"java":{"insertions":36,"deletions":14}}},{"hash":"6a2325e8bb64c88864ec6aa01b7b0ec461a670db","messageTitle":"Add Task.java","messageBody":"","fileTypesAndContributionMap":{"java":{"insertions":20,"deletions":0}}},{"hash":"995b0f69c91d7645a69362a7a738f8be656d0bfe","messageTitle":"Duke.java: use task and enable marking as done","messageBody":"","tags":["Level-3"],"fileTypesAndContributionMap":{"java":{"insertions":19,"deletions":10}}},{"hash":"44dd554afbe593644e6afb3d4a3b3bc35462f1c3","messageTitle":"Override toString of task to refactor code","messageBody":"","fileTypesAndContributionMap":{"java":{"insertions":7,"deletions":3}}}]},{"date":"2021-01-18","commitResults":[{"hash":"6fe144c8d2a25051764498438ada8fb1fea407ea","messageTitle":"Create Todo, Deadline and Event task types, refactored code to enable","messageBody":"","tags":["Level-4"],"fileTypesAndContributionMap":{"java":{"insertions":95,"deletions":22}}},{"hash":"b09f308e5d73068d74d1ad055fba7e3a8178feaa","messageTitle":"Setup automated tests using sample scripts","messageBody":"","tags":["A-TextUiTesting"],"fileTypesAndContributionMap":{"txt":{"insertions":12,"deletions":0},"sh":{"insertions":1,"deletions":1}}},{"hash":"d9dc8c1c909f8407e10cdfb4264e20270a4d6777","messageTitle":"Deal with whitespace properly and implement exceptions to catch invalid input","messageBody":"","tags":["Level-5"],"fileTypesAndContributionMap":{"txt":{"insertions":1,"deletions":1},"java":{"insertions":112,"deletions":38}}},{"hash":"fffdad967d8e7b0c6b582f3681c2dd859168ab49","messageTitle":"Duke.java: Add support for deleting tasks from the list","messageBody":"","fileTypesAndContributionMap":{"java":{"insertions":19,"deletions":1}}},{"hash":"552fb159eb6029f3efe2c0b95cd2e2289bddbf25","messageTitle":"test: check for delete task","messageBody":"","tags":["Level-6"],"fileTypesAndContributionMap":{"txt":{"insertions":7,"deletions":0}}}]},{"date":"2021-01-19","commitResults":[{"hash":"fba489b42cab16c08c427ab4107cc5b55710e217","messageTitle":"Use enums for functions","messageBody":"","tags":["A-Enums"],"fileTypesAndContributionMap":{"java":{"insertions":33,"deletions":12}}},{"hash":"f6b4092a1f1a062316150ecbde6d31e7de0a3288","messageTitle":"Refactor printing of lines","messageBody":"","fileTypesAndContributionMap":{"java":{"insertions":15,"deletions":38}}}]}]},"authorFileTypeContributionMap":{"kouyk":{"java":252,"md":0,"fxml":0,"sh":1,"bat":0,"gradle":0,"txt":19}},"authorContributionVariance":{"kouyk":10381.434},"authorDisplayNameMap":{"kouyk":"KOU ..KANG"}}
